setup.py
ee_grab_helpers/__init__.py
ee_grab_helpers/ee_grab_helpers.py
ee_grab_helpers/get_data.py
ee_grab_helpers.egg-info/PKG-INFO
ee_grab_helpers.egg-info/SOURCES.txt
ee_grab_helpers.egg-info/dependency_links.txt
ee_grab_helpers.egg-info/not-zip-safe
ee_grab_helpers.egg-info/requires.txt
ee_grab_helpers.egg-info/top_level.txt