Metadata-Version: 1.0
Name: ee-grab-helpers
Version: 0.1
Summary: Helper functions for the Google Earth Engine Python API
Home-page: https://github.com/JesJehle/earthEngineGrabR
Author: Janusch Jehle
Author-email: JesJehle@gmx.de
License: MIT
Platform: UNKNOWN
